writer_reader/__init__.py
writer_reader/cli.py
writer_reader/project.py
writer_reader/segmenter.py
writer_reader/server.py
writer_reader/static/editor.html
writer_reader-0.1.1.dist-info/METADATA
writer_reader-0.1.1.dist-info/WHEEL
writer_reader-0.1.1.dist-info/entry_points.txt
writer_reader-0.1.1.dist-info/RECORD
