Metadata-Version: 2.4
Name: writer-reader
Version: 0.1.1
Summary: Segment-based book manuscript editor with git integration
Project-URL: Homepage, https://github.com/bobmatnyc/writer-reader
Project-URL: Repository, https://github.com/bobmatnyc/writer-reader
Project-URL: Issues, https://github.com/bobmatnyc/writer-reader/issues
Author-email: Bob Matsuoka <bob@matsuoka.com>
License-Expression: MIT
Keywords: editor,git,manuscript,markdown,writing
Classifier: Development Status :: 3 - Alpha
Classifier: Environment :: Web Environment
Classifier: Framework :: Flask
Classifier: Intended Audience :: End Users/Desktop
Classifier: License :: OSI Approved :: MIT License
Classifier: Programming Language :: Python :: 3
Classifier: Programming Language :: Python :: 3.10
Classifier: Programming Language :: Python :: 3.11
Classifier: Programming Language :: Python :: 3.12
Classifier: Topic :: Text Processing :: Markup :: Markdown
Requires-Python: >=3.10
Requires-Dist: click>=8.0
Requires-Dist: flask-cors>=3.0
Requires-Dist: flask>=2.0
Requires-Dist: pyyaml>=6.0
Provides-Extra: dev
Requires-Dist: black>=23.0; extra == 'dev'
Requires-Dist: pytest-cov>=4.0; extra == 'dev'
Requires-Dist: pytest>=7.0; extra == 'dev'
Requires-Dist: ruff>=0.1.0; extra == 'dev'
